nequip/__init__.py
nequip/_version.py
nequip/ase/__init__.py
nequip/ase/nequip_calculator.py
nequip/ase/nosehoover.py
nequip/data/AtomicDataDict.py
nequip/data/__init__.py
nequip/data/_key_registry.py
nequip/data/_keys.py
nequip/data/_nl.py
nequip/data/_sampler.py
nequip/data/ase.py
nequip/data/dict.py
nequip/data/misc.py
nequip/data/modifier.py
nequip/data/stats.py
nequip/data/stats_manager.py
nequip/data/datamodule/_3bpa_datamodule.py
nequip/data/datamodule/__init__.py
nequip/data/datamodule/_ase_datamodule.py
nequip/data/datamodule/_base_datamodule.py
nequip/data/datamodule/coll_datamodule.py
nequip/data/datamodule/md22_datamodule.py
nequip/data/datamodule/rmd17_datamodule.py
nequip/data/datamodule/samd23_datamodule.py
nequip/data/datamodule/sgdml_datamodule.py
nequip/data/datamodule/tm23_datamodule.py
nequip/data/datamodule/water_datamodule.py
nequip/data/dataset/__init__.py
nequip/data/dataset/ase_dataset.py
nequip/data/dataset/base_datasets.py
nequip/data/dataset/hdf5_dataset.py
nequip/data/dataset/lmdb_dataset.py
nequip/data/dataset/npz_dataset.py
nequip/data/dataset/test_data.py
nequip/data/dataset/utils.py
nequip/data/dataset_stats/MPTrj.yaml
nequip/data/dataset_stats/MatPES.yaml
nequip/data/dataset_stats/OMat.yaml
nequip/data/transforms/__init__.py
nequip/data/transforms/cell_utils.py
nequip/data/transforms/neighborlist.py
nequip/data/transforms/stress_utils.py
nequip/data/transforms/type_mapper.py
nequip/integrations/__init__.py
nequip/integrations/torchsim.py
nequip/integrations/lammps_mliap/create_lmp_mliap_file.py
nequip/integrations/lammps_mliap/lmp_mliap_wrapper.py
nequip/model/__init__.py
nequip/model/modify_utils.py
nequip/model/nequip_models.py
nequip/model/pair_potential.py
nequip/model/utils.py
nequip/model/inference_models/__init__.py
nequip/model/inference_models/aotinductor.py
nequip/model/inference_models/compiled.py
nequip/model/inference_models/torchscript.py
nequip/model/saved_models/__init__.py
nequip/model/saved_models/_utils.py
nequip-0.16.2.dist-info/licenses/AUTHORS.md
nequip-0.16.2.dist-info/licenses/LICENSE
nequip-0.16.2.dist-info/METADATA
nequip-0.16.2.dist-info/WHEEL
nequip-0.16.2.dist-info/entry_points.txt
nequip-0.16.2.dist-info/top_level.txt
nequip-0.16.2.dist-info/RECORD
