Metadata-Version: 2.4
Name: nequip
Version: 0.16.2
Summary: NequIP is an open-source code for building E(3)-equivariant interatomic potentials.
Author-email: The NequIP Developers <allegro-nequip@g.harvard.edu>
License: MIT License
Project-URL: Homepage, https://github.com/mir-group/nequip
Project-URL: Repository, https://github.com/mir-group/nequip.git
Project-URL: Documentation, https://nequip.readthedocs.io/
Requires-Python: >=3.10
License-File: LICENSE
License-File: AUTHORS.md
Requires-Dist: torch>=2.2.0
Requires-Dist: numpy
Requires-Dist: matscipy
Requires-Dist: ase
Requires-Dist: lmdb
Requires-Dist: tqdm
Requires-Dist: e3nn<0.6.0,>=0.5.9
Requires-Dist: pyyaml
Requires-Dist: importlib_metadata; python_version < "3.10"
Requires-Dist: hydra-core
Requires-Dist: lightning
Requires-Dist: torchmetrics>=1.6.0
Requires-Dist: requests
Dynamic: license-file
